<?xml version="1.0" encoding="UTF-8"?><?xml-stylesheet type='text/xsl' href='_UpgradeReport_Files/UpgradeReport.xslt'?><UpgradeLog>
<Properties><Property Name="Solution" Value="DCarS">
</Property><Property Name="Solution File" Value="C:\Users\mhossain2\Dropbox\Public\My VisualStudio\Visual CS\DCarS\DCarS.sln">
</Property><Property Name="User Options File" Value="C:\Users\mhossain2\Dropbox\Public\My VisualStudio\Visual CS\DCarS\DCarS.suo">
</Property><Property Name="Date" Value="Tuesday, November 13, 2012">
</Property><Property Name="Time" Value="12:23 PM">
</Property><Property Name="Log Number" Value="2">
</Property></Properties><Event ErrorLevel="0" Project="" Source="DCarS.sln" Description="File successfully backed up as C:\Users\mhossain2\Dropbox\Public\My VisualStudio\Visual CS\DCarS\Backup\DCarS.sln">
</Event><Event ErrorLevel="0" Project="" Source="DCarS.suo" Description="File successfully backed up as C:\Users\mhossain2\Dropbox\Public\My VisualStudio\Visual CS\DCarS\Backup\DCarS.suo">
</Event><Event ErrorLevel="0" Project="DCarS" Source="DCarS\DCarS.csproj" Description="Project file successfully backed up as C:\Users\mhossain2\Dropbox\Public\My VisualStudio\Visual CS\DCarS\Backup\DCarS\DCarS.csproj">
</Event><Event ErrorLevel="0" Project="DCarS" Source="DCarS\DCarS.csproj.user" Description="Project user file successfully backed up as C:\Users\mhossain2\Dropbox\Public\My VisualStudio\Visual CS\DCarS\Backup\DCarS\DCarS.csproj.user">
</Event><Event ErrorLevel="0" Project="DCarS" Source="DCarS\California.cs" Description="File successfully backed up as C:\Users\mhossain2\Dropbox\Public\My VisualStudio\Visual CS\DCarS\Backup\DCarS\California.cs">
</Event><Event ErrorLevel="0" Project="DCarS" Source="DCarS\California.Designer.cs" Description="File successfully backed up as C:\Users\mhossain2\Dropbox\Public\My VisualStudio\Visual CS\DCarS\Backup\DCarS\California.Designer.cs">
</Event><Event ErrorLevel="0" Project="DCarS" Source="DCarS\DrivingTest1.cs" Description="File successfully backed up as C:\Users\mhossain2\Dropbox\Public\My VisualStudio\Visual CS\DCarS\Backup\DCarS\DrivingTest1.cs">
</Event><Event ErrorLevel="0" Project="DCarS" Source="DCarS\DrivingTest1.Designer.cs" Description="File successfully backed up as C:\Users\mhossain2\Dropbox\Public\My VisualStudio\Visual CS\DCarS\Backup\DCarS\DrivingTest1.Designer.cs">
</Event><Event ErrorLevel="0" Project="DCarS" Source="DCarS\Form1.cs" Description="File successfully backed up as C:\Users\mhossain2\Dropbox\Public\My VisualStudio\Visual CS\DCarS\Backup\DCarS\Form1.cs">
</Event><Event ErrorLevel="0" Project="DCarS" Source="DCarS\Form1.Designer.cs" Description="File successfully backed up as C:\Users\mhossain2\Dropbox\Public\My VisualStudio\Visual CS\DCarS\Backup\DCarS\Form1.Designer.cs">
</Event><Event ErrorLevel="0" Project="DCarS" Source="DCarS\Nevada.cs" Description="File successfully backed up as C:\Users\mhossain2\Dropbox\Public\My VisualStudio\Visual CS\DCarS\Backup\DCarS\Nevada.cs">
</Event><Event ErrorLevel="0" Project="DCarS" Source="DCarS\Nevada.Designer.cs" Description="File successfully backed up as C:\Users\mhossain2\Dropbox\Public\My VisualStudio\Visual CS\DCarS\Backup\DCarS\Nevada.Designer.cs">
</Event><Event ErrorLevel="0" Project="DCarS" Source="DCarS\New York.cs" Description="File successfully backed up as C:\Users\mhossain2\Dropbox\Public\My VisualStudio\Visual CS\DCarS\Backup\DCarS\New York.cs">
</Event><Event ErrorLevel="0" Project="DCarS" Source="DCarS\New York.Designer.cs" Description="File successfully backed up as C:\Users\mhossain2\Dropbox\Public\My VisualStudio\Visual CS\DCarS\Backup\DCarS\New York.Designer.cs">
</Event><Event ErrorLevel="0" Project="DCarS" Source="DCarS\Program.cs" Description="File successfully backed up as C:\Users\mhossain2\Dropbox\Public\My VisualStudio\Visual CS\DCarS\Backup\DCarS\Program.cs">
</Event><Event ErrorLevel="0" Project="DCarS" Source="DCarS\Properties\AssemblyInfo.cs" Description="File successfully backed up as C:\Users\mhossain2\Dropbox\Public\My VisualStudio\Visual CS\DCarS\Backup\DCarS\Properties\AssemblyInfo.cs">
</Event><Event ErrorLevel="0" Project="DCarS" Source="DCarS\Properties\Resources.Designer.cs" Description="File successfully backed up as C:\Users\mhossain2\Dropbox\Public\My VisualStudio\Visual CS\DCarS\Backup\DCarS\Properties\Resources.Designer.cs">
</Event><Event ErrorLevel="0" Project="DCarS" Source="DCarS\QuestionAnswer.cs" Description="File successfully backed up as C:\Users\mhossain2\Dropbox\Public\My VisualStudio\Visual CS\DCarS\Backup\DCarS\QuestionAnswer.cs">
</Event><Event ErrorLevel="0" Project="DCarS" Source="DCarS\QuestionAnswer.Designer.cs" Description="File successfully backed up as C:\Users\mhossain2\Dropbox\Public\My VisualStudio\Visual CS\DCarS\Backup\DCarS\QuestionAnswer.Designer.cs">
</Event><Event ErrorLevel="0" Project="DCarS" Source="DCarS\Rules.cs" Description="File successfully backed up as C:\Users\mhossain2\Dropbox\Public\My VisualStudio\Visual CS\DCarS\Backup\DCarS\Rules.cs">
</Event><Event ErrorLevel="0" Project="DCarS" Source="DCarS\Rules.Designer.cs" Description="File successfully backed up as C:\Users\mhossain2\Dropbox\Public\My VisualStudio\Visual CS\DCarS\Backup\DCarS\Rules.Designer.cs">
</Event><Event ErrorLevel="0" Project="DCarS" Source="DCarS\StateLaws.cs" Description="File successfully backed up as C:\Users\mhossain2\Dropbox\Public\My VisualStudio\Visual CS\DCarS\Backup\DCarS\StateLaws.cs">
</Event><Event ErrorLevel="0" Project="DCarS" Source="DCarS\StateLaws.Designer.cs" Description="File successfully backed up as C:\Users\mhossain2\Dropbox\Public\My VisualStudio\Visual CS\DCarS\Backup\DCarS\StateLaws.Designer.cs">
</Event><Event ErrorLevel="0" Project="DCarS" Source="DCarS\Texas.cs" Description="File successfully backed up as C:\Users\mhossain2\Dropbox\Public\My VisualStudio\Visual CS\DCarS\Backup\DCarS\Texas.cs">
</Event><Event ErrorLevel="0" Project="DCarS" Source="DCarS\Texas.Designer.cs" Description="File successfully backed up as C:\Users\mhossain2\Dropbox\Public\My VisualStudio\Visual CS\DCarS\Backup\DCarS\Texas.Designer.cs">
</Event><Event ErrorLevel="0" Project="DCarS" Source="DCarS\California.resx" Description="File successfully backed up as C:\Users\mhossain2\Dropbox\Public\My VisualStudio\Visual CS\DCarS\Backup\DCarS\California.resx">
</Event><Event ErrorLevel="0" Project="DCarS" Source="DCarS\DrivingTest1.resx" Description="File successfully backed up as C:\Users\mhossain2\Dropbox\Public\My VisualStudio\Visual CS\DCarS\Backup\DCarS\DrivingTest1.resx">
</Event><Event ErrorLevel="0" Project="DCarS" Source="DCarS\Form1.resx" Description="File successfully backed up as C:\Users\mhossain2\Dropbox\Public\My VisualStudio\Visual CS\DCarS\Backup\DCarS\Form1.resx">
</Event><Event ErrorLevel="0" Project="DCarS" Source="DCarS\Nevada.resx" Description="File successfully backed up as C:\Users\mhossain2\Dropbox\Public\My VisualStudio\Visual CS\DCarS\Backup\DCarS\Nevada.resx">
</Event><Event ErrorLevel="0" Project="DCarS" Source="DCarS\New York.resx" Description="File successfully backed up as C:\Users\mhossain2\Dropbox\Public\My VisualStudio\Visual CS\DCarS\Backup\DCarS\New York.resx">
</Event><Event ErrorLevel="0" Project="DCarS" Source="DCarS\Properties\Resources.resx" Description="File successfully backed up as C:\Users\mhossain2\Dropbox\Public\My VisualStudio\Visual CS\DCarS\Backup\DCarS\Properties\Resources.resx">
</Event><Event ErrorLevel="0" Project="DCarS" Source="DCarS\QuestionAnswer.resx" Description="File successfully backed up as C:\Users\mhossain2\Dropbox\Public\My VisualStudio\Visual CS\DCarS\Backup\DCarS\QuestionAnswer.resx">
</Event><Event ErrorLevel="0" Project="DCarS" Source="DCarS\Rules.resx" Description="File successfully backed up as C:\Users\mhossain2\Dropbox\Public\My VisualStudio\Visual CS\DCarS\Backup\DCarS\Rules.resx">
</Event><Event ErrorLevel="0" Project="DCarS" Source="DCarS\StateLaws.resx" Description="File successfully backed up as C:\Users\mhossain2\Dropbox\Public\My VisualStudio\Visual CS\DCarS\Backup\DCarS\StateLaws.resx">
</Event><Event ErrorLevel="0" Project="DCarS" Source="DCarS\Texas.resx" Description="File successfully backed up as C:\Users\mhossain2\Dropbox\Public\My VisualStudio\Visual CS\DCarS\Backup\DCarS\Texas.resx">
</Event><Event ErrorLevel="0" Project="DCarS" Source="DCarS\DCarS.csproj" Description="Project converted successfully">
</Event><Event ErrorLevel="3" Project="DCarS" Source="DCarS\DCarS.csproj" Description="Converted">
</Event><Event ErrorLevel="0" Project="" Source="DCarS.sln" Description="The solution file does not require conversion.">
</Event><Event ErrorLevel="3" Project="" Source="DCarS.sln" Description="No Conversion Required">
</Event></UpgradeLog>